{
    "Person2": {
        "month": 4,
        "day": 30
    },
    "Person3": {
        "month": 5,
        "day": 23
    },
    "Person4": {
        "month": 3,
        "day": 2
    },
    "Person5": {
        "month": 2,
        "day": 2
    },
    "Person49": {
        "month": 9,
        "day": 4
    },
    "Person50": {
        "month": 9,
        "day": 21
    },
    "Person51": {
        "month": 4,
        "day": 18
    },
    "Person52": {
        "month": 3,
        "day": 21
    },
    "Person53": {
        "month": 12,
        "day": 29
    },
    "Person54": {
        "month": 12,
        "day": 19
    },
    "Person55": {
        "month": 7,
        "day": 9
    },
    "Person56": {
        "month": 10,
        "day": 5
    },
    "Person57": {
        "month": 5,
        "day": 7
    },
    "Person58": {
        "month": 11,
        "day": 20
    },
    "Person59": {
        "month": 7,
        "day": 30
    },
    "Person60": {
        "month": 1,
        "day": 13
    },
    "Person61": {
        "month": 6,
        "day": 11
    },
    "Person62": {
        "month": 4,
        "day": 10
    },
    "Person63": {
        "month": 5,
        "day": 12
    },
    "Person64": {
        "month": 4,
        "day": 27
    },
    "Person65": {
        "month": 9,
        "day": 4
    },
    "Person66": {
        "month": 2,
        "day": 5
    },
    "Person67": {
        "month": 12,
        "day": 27
    },
    "Person68": {
        "month": 7,
        "day": 24
    },
    "Person69": {
        "month": 2,
        "day": 12
    },
    "Person70": {
        "month": 1,
        "day": 22
    },
    "Person71": {
        "month": 8,
        "day": 22
    },
    "Person72": {
        "month": 8,
        "day": 12
    },
    "Person73": {
        "month": 7,
        "day": 24
    },
    "Person74": {
        "month": 6,
        "day": 17
    },
    "Person75": {
        "month": 9,
        "day": 26
    },
    "Person76": {
        "month": 9,
        "day": 14
    },
    "Person77": {
        "month": 12,
        "day": 11
    },
    "Person78": {
        "month": 6,
        "day": 15
    },
    "Person79": {
        "month": 5,
        "day": 31
    },
    "Person80": {
        "month": 7,
        "day": 28
    },
    "Person81": {
        "month": 8,
        "day": 14
    },
    "Person82": {
        "month": 10,
        "day": 4
    },
    "Person83": {
        "month": 8,
        "day": 1
    },
    "Person84": {
        "month": 5,
        "day": 26
    },
    "Person85": {
        "month": 1,
        "day": 14
    },
    "Person86": {
        "month": 5,
        "day": 15
    },
    "Person87": {
        "month": 7,
        "day": 2
    },
    "Person88": {
        "month": 11,
        "day": 13
    },
    "Person89": {
        "month": 3,
        "day": 21
    },
    "Person90": {
        "month": 10,
        "day": 18
    },
    "Person91": {
        "month": 4,
        "day": 18
    },
    "Person92": {
        "month": 7,
        "day": 3
    },
    "Person93": {
        "month": 9,
        "day": 28
    },
    "Person94": {
        "month": 3,
        "day": 2
    },
    "Person95": {
        "month": 2,
        "day": 16
    },
    "Person96": {
        "month": 3,
        "day": 15
    },
    "Person97": {
        "month": 5,
        "day": 15
    },
    "Person98": {
        "month": 6,
        "day": 2
    },
    "Person99": {
        "month": 11,
        "day": 10
    },
    "Person100": {
        "month": 3,
        "day": 20
    },
    "Person101": {
        "month": 5,
        "day": 19
    },
    "Person102": {
        "month": 3,
        "day": 29
    },
    "Person103": {
        "month": 12,
        "day": 18
    },
    "Person104": {
        "month": 11,
        "day": 9
    },
    "Person105": {
        "month": 4,
        "day": 27
    },
    "Person106": {
        "month": 2,
        "day": 21
    },
    "Person107": {
        "month": 8,
        "day": 27
    },
    "Person108": {
        "month": 11,
        "day": 24
    },
    "Person109": {
        "month": 6,
        "day": 18
    },
    "Person110": {
        "month": 6,
        "day": 12
    },
    "Person111": {
        "month": 7,
        "day": 17
    },
    "Person112": {
        "month": 5,
        "day": 16
    },
    "Person113": {
        "month": 11,
        "day": 28
    },
    "Person114": {
        "month": 12,
        "day": 17
    },
    "Person115": {
        "month": 5,
        "day": 16
    },
    "Person116": {
        "month": 3,
        "day": 20
    },
    "Person117": {
        "month": 5,
        "day": 13
    },
    "Person118": {
        "month": 8,
        "day": 14
    },
    "Person119": {
        "month": 7,
        "day": 14
    },
    "Person120": {
        "month": 2,
        "day": 21
    },
    "Person121": {
        "month": 2,
        "day": 4
    },
    "Person122": {
        "month": 5,
        "day": 8
    },
    "Person123": {
        "month": 2,
        "day": 2
    },
    "Person124": {
        "month": 8,
        "day": 10
    },
    "Person125": {
        "month": 5,
        "day": 25
    },
    "Person126": {
        "month": 10,
        "day": 15
    },
    "Person127": {
        "month": 11,
        "day": 16
    },
    "Person128": {
        "month": 11,
        "day": 4
    },
    "Person129": {
        "month": 3,
        "day": 28
    },
    "Person130": {
        "month": 9,
        "day": 23
    },
    "Person131": {
        "month": 3,
        "day": 31
    },
    "Person132": {
        "month": 2,
        "day": 18
    },
    "Person133": {
        "month": 8,
        "day": 18
    },
    "Person134": {
        "month": 11,
        "day": 7
    },
    "Person135": {
        "month": 9,
        "day": 21
    },
    "Person136": {
        "month": 3,
        "day": 15
    },
    "Person137": {
        "month": 11,
        "day": 2
    },
    "Person138": {
        "month": 11,
        "day": 22
    },
    "Person139": {
        "month": 6,
        "day": 3
    },
    "Person140": {
        "month": 8,
        "day": 11
    },
    "Person141": {
        "month": 10,
        "day": 22
    },
    "Person142": {
        "month": 2,
        "day": 13
    },
    "Person143": {
        "month": 11,
        "day": 26
    },
    "Person144": {
        "month": 12,
        "day": 18
    },
    "Person145": {
        "month": 6,
        "day": 30
    },
    "Person146": {
        "month": 3,
        "day": 16
    },
    "Person147": {
        "month": 9,
        "day": 3
    },
    "Person148": {
        "month": 3,
        "day": 16
    },
    "Person149": {
        "month": 1,
        "day": 30
    },
    "Person150": {
        "month": 6,
        "day": 8
    },
    "Person151": {
        "month": 3,
        "day": 6
    },
    "Person152": {
        "month": 2,
        "day": 13
    },
    "Person153": {
        "month": 9,
        "day": 25
    },
    "Person154": {
        "month": 6,
        "day": 7
    },
    "Person155": {
        "month": 2,
        "day": 17
    },
    "Person156": {
        "month": 11,
        "day": 13
    },
    "Person157": {
        "month": 9,
        "day": 9
    },
    "Person158": {
        "month": 7,
        "day": 13
    },
    "Person159": {
        "month": 2,
        "day": 28
    },
    "Person160": {
        "month": 11,
        "day": 18
    },
    "Person161": {
        "month": 3,
        "day": 24
    },
    "Person162": {
        "month": 1,
        "day": 11
    },
    "Person163": {
        "month": 8,
        "day": 24
    },
    "Person164": {
        "month": 2,
        "day": 2
    },
    "Person165": {
        "month": 12,
        "day": 10
    },
    "Person166": {
        "month": 2,
        "day": 7
    },
    "Person167": {
        "month": 2,
        "day": 14
    },
    "Person168": {
        "month": 4,
        "day": 22
    },
    "Person169": {
        "month": 3,
        "day": 25
    },
    "Person170": {
        "month": 5,
        "day": 2
    },
    "Person171": {
        "month": 1,
        "day": 12
    },
    "Person172": {
        "month": 9,
        "day": 11
    },
    "Person173": {
        "month": 6,
        "day": 12
    },
    "Person174": {
        "month": 7,
        "day": 19
    },
    "Person175": {
        "month": 11,
        "day": 26
    },
    "Person176": {
        "month": 1,
        "day": 14
    },
    "Person177": {
        "month": 9,
        "day": 28
    },
    "Person178": {
        "month": 7,
        "day": 17
    },
    "Person179": {
        "month": 12,
        "day": 9
    },
    "Person180": {
        "month": 5,
        "day": 5
    },
    "Person181": {
        "month": 11,
        "day": 24
    },
    "Person182": {
        "month": 7,
        "day": 4
    },
    "Person183": {
        "month": 11,
        "day": 11
    },
    "Person184": {
        "month": 9,
        "day": 22
    },
    "Person185": {
        "month": 3,
        "day": 13
    },
    "Person186": {
        "month": 5,
        "day": 12
    },
    "Person187": {
        "month": 2,
        "day": 1
    },
    "Person188": {
        "month": 10,
        "day": 18
    },
    "Person189": {
        "month": 12,
        "day": 19
    },
    "Person190": {
        "month": 3,
        "day": 31
    },
    "Person191": {
        "month": 12,
        "day": 16
    },
    "Person192": {
        "month": 5,
        "day": 17
    },
    "Person193": {
        "month": 4,
        "day": 22
    },
    "Person194": {
        "month": 8,
        "day": 6
    },
    "Person195": {
        "month": 7,
        "day": 20
    },
    "Person196": {
        "month": 3,
        "day": 6
    },
    "Person197": {
        "month": 3,
        "day": 26
    },
    "Person198": {
        "month": 11,
        "day": 20
    },
    "Person199": {
        "month": 12,
        "day": 2
    },
    "Person200": {
        "month": 3,
        "day": 16
    },
    "Person201": {
        "month": 11,
        "day": 13
    },
    "Person202": {
        "month": 1,
        "day": 17
    },
    "Person203": {
        "month": 12,
        "day": 18
    },
    "Person204": {
        "month": 10,
        "day": 18
    },
    "Person205": {
        "month": 8,
        "day": 4
    },
    "Person206": {
        "month": 4,
        "day": 16
    },
    "Person207": {
        "month": 6,
        "day": 27
    },
    "Person208": {
        "month": 1,
        "day": 16
    },
    "Person209": {
        "month": 12,
        "day": 3
    },
    "Person210": {
        "month": 9,
        "day": 2
    },
    "Person211": {
        "month": 7,
        "day": 16
    },
    "Person212": {
        "month": 12,
        "day": 18
    },
    "Person213": {
        "month": 10,
        "day": 28
    },
    "Person214": {
        "month": 5,
        "day": 30
    },
    "Person215": {
        "month": 7,
        "day": 30
    },
    "Person216": {
        "month": 7,
        "day": 5
    },
    "Person217": {
        "month": 5,
        "day": 10
    },
    "Person218": {
        "month": 6,
        "day": 20
    },
    "Person219": {
        "month": 10,
        "day": 20
    },
    "Person220": {
        "month": 9,
        "day": 11
    },
    "Person221": {
        "month": 2,
        "day": 9
    },
    "Person222": {
        "month": 4,
        "day": 22
    },
    "Person223": {
        "month": 6,
        "day": 6
    },
    "Person224": {
        "month": 11,
        "day": 5
    },
    "Person225": {
        "month": 7,
        "day": 28
    },
    "Person226": {
        "month": 6,
        "day": 16
    },
    "Person227": {
        "month": 5,
        "day": 21
    },
    "Person228": {
        "month": 8,
        "day": 17
    },
    "Person229": {
        "month": 4,
        "day": 3
    },
    "Person230": {
        "month": 8,
        "day": 20
    },
    "Person231": {
        "month": 12,
        "day": 21
    },
    "Person232": {
        "month": 5,
        "day": 3
    },
    "Person233": {
        "month": 4,
        "day": 30
    },
    "Person234": {
        "month": 9,
        "day": 16
    },
    "Person235": {
        "month": 8,
        "day": 5
    },
    "Person236": {
        "month": 10,
        "day": 29
    },
    "Person237": {
        "month": 4,
        "day": 22
    },
    "Person238": {
        "month": 10,
        "day": 24
    },
    "Person239": {
        "month": 2,
        "day": 23
    },
    "Person240": {
        "month": 5,
        "day": 13
    },
    "Person241": {
        "month": 10,
        "day": 28
    },
    "Person242": {
        "month": 1,
        "day": 19
    },
    "Person243": {
        "month": 9,
        "day": 4
    },
    "Person244": {
        "month": 8,
        "day": 19
    },
    "Person245": {
        "month": 7,
        "day": 9
    },
    "Person246": {
        "month": 1,
        "day": 11
    },
    "Person247": {
        "month": 1,
        "day": 30
    },
    "Person248": {
        "month": 11,
        "day": 9
    },
    "Person249": {
        "month": 10,
        "day": 8
    },
    "Person250": {
        "month": 1,
        "day": 7
    },
    "Person251": {
        "month": 2,
        "day": 25
    },
    "Person252": {
        "month": 9,
        "day": 21
    },
    "Person253": {
        "month": 5,
        "day": 6
    },
    "Person254": {
        "month": 12,
        "day": 17
    },
    "Person255": {
        "month": 3,
        "day": 14
    },
    "Person256": {
        "month": 5,
        "day": 20
    },
    "Person257": {
        "month": 3,
        "day": 5
    },
    "Person258": {
        "month": 7,
        "day": 8
    },
    "Person259": {
        "month": 5,
        "day": 20
    },
    "Person260": {
        "month": 12,
        "day": 11
    },
    "Person261": {
        "month": 12,
        "day": 1
    },
    "Person262": {
        "month": 11,
        "day": 15
    },
    "Person263": {
        "month": 2,
        "day": 6
    },
    "Person264": {
        "month": 12,
        "day": 24
    },
    "Person265": {
        "month": 7,
        "day": 7
    },
    "Person266": {
        "month": 5,
        "day": 7
    },
    "Person267": {
        "month": 10,
        "day": 25
    },
    "Person268": {
        "month": 5,
        "day": 28
    },
    "Person269": {
        "month": 6,
        "day": 25
    },
    "Person270": {
        "month": 1,
        "day": 8
    },
    "Person271": {
        "month": 1,
        "day": 17
    },
    "Person272": {
        "month": 7,
        "day": 23
    },
    "Person273": {
        "month": 12,
        "day": 4
    },
    "Person274": {
        "month": 4,
        "day": 13
    },
    "Person275": {
        "month": 11,
        "day": 6
    },
    "Person276": {
        "month": 6,
        "day": 6
    },
    "Person277": {
        "month": 2,
        "day": 16
    },
    "Person278": {
        "month": 11,
        "day": 18
    },
    "Person279": {
        "month": 7,
        "day": 16
    },
    "Person280": {
        "month": 10,
        "day": 16
    },
    "Person281": {
        "month": 2,
        "day": 9
    },
    "Person282": {
        "month": 3,
        "day": 24
    },
    "Person283": {
        "month": 11,
        "day": 21
    },
    "Person284": {
        "month": 6,
        "day": 12
    },
    "Person285": {
        "month": 11,
        "day": 14
    },
    "Person286": {
        "month": 4,
        "day": 8
    },
    "Person287": {
        "month": 6,
        "day": 16
    },
    "Person288": {
        "month": 5,
        "day": 21
    },
    "Person289": {
        "month": 8,
        "day": 21
    },
    "Person290": {
        "month": 4,
        "day": 22
    },
    "Person291": {
        "month": 7,
        "day": 24
    },
    "Person292": {
        "month": 6,
        "day": 24
    },
    "Person293": {
        "month": 5,
        "day": 5
    },
    "Person294": {
        "month": 12,
        "day": 13
    },
    "Person295": {
        "month": 3,
        "day": 31
    },
    "Person296": {
        "month": 7,
        "day": 15
    },
    "Person297": {
        "month": 5,
        "day": 24
    },
    "Person298": {
        "month": 5,
        "day": 8
    },
    "Person299": {
        "month": 12,
        "day": 19
    },
    "Person300": {
        "month": 7,
        "day": 1
    },
    "Person301": {
        "month": 12,
        "day": 26
    },
    "Person302": {
        "month": 2,
        "day": 19
    },
    "Person303": {
        "month": 9,
        "day": 13
    },
    "Person304": {
        "month": 12,
        "day": 5
    },
    "Person305": {
        "month": 12,
        "day": 25
    },
    "Person306": {
        "month": 3,
        "day": 24
    },
    "Person307": {
        "month": 1,
        "day": 24
    },
    "Person308": {
        "month": 6,
        "day": 12
    },
    "Person309": {
        "month": 3,
        "day": 18
    },
    "Person310": {
        "month": 9,
        "day": 24
    },
    "Person311": {
        "month": 12,
        "day": 27
    },
    "Person312": {
        "month": 4,
        "day": 28
    },
    "Person313": {
        "month": 1,
        "day": 21
    },
    "Person314": {
        "month": 1,
        "day": 15
    },
    "Person315": {
        "month": 2,
        "day": 4
    },
    "Person316": {
        "month": 12,
        "day": 30
    },
    "Person317": {
        "month": 2,
        "day": 20
    },
    "Person318": {
        "month": 10,
        "day": 7
    },
    "Person319": {
        "month": 3,
        "day": 25
    },
    "Person320": {
        "month": 1,
        "day": 14
    },
    "Person321": {
        "month": 5,
        "day": 29
    },
    "Person322": {
        "month": 6,
        "day": 2
    },
    "Person323": {
        "month": 12,
        "day": 12
    },
    "Person324": {
        "month": 4,
        "day": 28
    },
    "Person325": {
        "month": 5,
        "day": 24
    },
    "Person326": {
        "month": 2,
        "day": 14
    },
    "Person327": {
        "month": 4,
        "day": 24
    },
    "Person328": {
        "month": 6,
        "day": 18
    },
    "Person329": {
        "month": 9,
        "day": 30
    },
    "Person330": {
        "month": 2,
        "day": 11
    },
    "Person331": {
        "month": 10,
        "day": 23
    },
    "Person332": {
        "month": 3,
        "day": 29
    },
    "Person333": {
        "month": 9,
        "day": 16
    },
    "Person334": {
        "month": 3,
        "day": 5
    },
    "Person335": {
        "month": 3,
        "day": 30
    },
    "Person336": {
        "month": 11,
        "day": 11
    },
    "Person337": {
        "month": 2,
        "day": 18
    },
    "Person338": {
        "month": 4,
        "day": 21
    },
    "Person339": {
        "month": 2,
        "day": 16
    },
    "Person340": {
        "month": 9,
        "day": 7
    },
    "Person341": {
        "month": 9,
        "day": 7
    },
    "Person342": {
        "month": 8,
        "day": 27
    },
    "Person343": {
        "month": 5,
        "day": 8
    },
    "Person344": {
        "month": 10,
        "day": 6
    },
    "Person345": {
        "month": 5,
        "day": 24
    },
    "Person346": {
        "month": 2,
        "day": 16
    },
    "Person347": {
        "month": 6,
        "day": 6
    },
    "Person348": {
        "month": 10,
        "day": 10
    },
    "Person349": {
        "month": 9,
        "day": 23
    },
    "Person350": {
        "month": 9,
        "day": 28
    },
    "Person351": {
        "month": 5,
        "day": 5
    },
    "Person352": {
        "month": 3,
        "day": 26
    },
    "Person353": {
        "month": 7,
        "day": 23
    },
    "Person354": {
        "month": 9,
        "day": 5
    },
    "Person355": {
        "month": 5,
        "day": 5
    },
    "Person356": {
        "month": 1,
        "day": 10
    },
    "Person357": {
        "month": 3,
        "day": 23
    },
    "Person358": {
        "month": 8,
        "day": 12
    },
    "Person359": {
        "month": 3,
        "day": 25
    },
    "Person360": {
        "month": 1,
        "day": 18
    },
    "Person361": {
        "month": 10,
        "day": 25
    },
    "Person362": {
        "month": 5,
        "day": 7
    },
    "Person363": {
        "month": 2,
        "day": 13
    },
    "Person364": {
        "month": 8,
        "day": 14
    },
    "Person365": {
        "month": 10,
        "day": 7
    },
    "Person366": {
        "month": 12,
        "day": 10
    },
    "Person367": {
        "month": 5,
        "day": 10
    },
    "Person368": {
        "month": 2,
        "day": 13
    },
    "Person369": {
        "month": 1,
        "day": 14
    },
    "Person370": {
        "month": 4,
        "day": 26
    },
    "Person371": {
        "month": 11,
        "day": 5
    },
    "Person372": {
        "month": 10,
        "day": 15
    },
    "Person373": {
        "month": 3,
        "day": 19
    },
    "Person374": {
        "month": 10,
        "day": 21
    },
    "Person375": {
        "month": 1,
        "day": 3
    },
    "Person376": {
        "month": 11,
        "day": 8
    },
    "Person377": {
        "month": 2,
        "day": 1
    },
    "Person378": {
        "month": 10,
        "day": 16
    },
    "Person379": {
        "month": 3,
        "day": 26
    },
    "Person380": {
        "month": 12,
        "day": 31
    },
    "Person381": {
        "month": 5,
        "day": 11
    },
    "Person382": {
        "month": 6,
        "day": 18
    },
    "Person383": {
        "month": 10,
        "day": 30
    },
    "Person384": {
        "month": 9,
        "day": 29
    },
    "Person385": {
        "month": 11,
        "day": 7
    },
    "Person386": {
        "month": 11,
        "day": 20
    },
    "Person387": {
        "month": 2,
        "day": 11
    },
    "Person388": {
        "month": 3,
        "day": 11
    },
    "Person389": {
        "month": 8,
        "day": 31
    },
    "Person390": {
        "month": 9,
        "day": 2
    },
    "Person391": {
        "month": 2,
        "day": 16
    },
    "Person392": {
        "month": 7,
        "day": 10
    },
    "Person393": {
        "month": 12,
        "day": 15
    },
    "Person394": {
        "month": 2,
        "day": 2
    },
    "Person395": {
        "month": 10,
        "day": 11
    },
    "Person396": {
        "month": 1,
        "day": 21
    },
    "Person397": {
        "month": 8,
        "day": 4
    },
    "Person398": {
        "month": 11,
        "day": 1
    },
    "Person399": {
        "month": 6,
        "day": 28
    },
    "Person400": {
        "month": 10,
        "day": 27
    },
    "Person401": {
        "month": 7,
        "day": 17
    },
    "Person402": {
        "month": 12,
        "day": 14
    },
    "Person403": {
        "month": 4,
        "day": 13
    },
    "Person404": {
        "month": 9,
        "day": 22
    },
    "Person405": {
        "month": 7,
        "day": 11
    },
    "Person406": {
        "month": 5,
        "day": 10
    },
    "Person407": {
        "month": 7,
        "day": 11
    },
    "Person408": {
        "month": 2,
        "day": 23
    },
    "Person409": {
        "month": 10,
        "day": 9
    },
    "Person410": {
        "month": 3,
        "day": 23
    },
    "Person411": {
        "month": 8,
        "day": 20
    },
    "Person412": {
        "month": 12,
        "day": 28
    },
    "Person413": {
        "month": 11,
        "day": 21
    },
    "Person414": {
        "month": 1,
        "day": 19
    },
    "Person415": {
        "month": 3,
        "day": 8
    },
    "Person416": {
        "month": 12,
        "day": 22
    },
    "Person417": {
        "month": 4,
        "day": 24
    },
    "Person418": {
        "month": 6,
        "day": 24
    },
    "Person419": {
        "month": 3,
        "day": 4
    },
    "Person420": {
        "month": 11,
        "day": 28
    },
    "Person421": {
        "month": 6,
        "day": 3
    },
    "Person422": {
        "month": 12,
        "day": 14
    },
    "Person423": {
        "month": 9,
        "day": 22
    },
    "Person424": {
        "month": 10,
        "day": 11
    },
    "Person425": {
        "month": 7,
        "day": 6
    },
    "Person426": {
        "month": 5,
        "day": 8
    },
    "Person427": {
        "month": 4,
        "day": 23
    },
    "Person428": {
        "month": 8,
        "day": 18
    },
    "Person429": {
        "month": 12,
        "day": 23
    },
    "Person430": {
        "month": 8,
        "day": 13
    },
    "Person431": {
        "month": 4,
        "day": 2
    },
    "Person432": {
        "month": 7,
        "day": 6
    },
    "Person433": {
        "month": 10,
        "day": 28
    },
    "Person434": {
        "month": 7,
        "day": 23
    },
    "Person435": {
        "month": 11,
        "day": 28
    },
    "Person436": {
        "month": 1,
        "day": 29
    },
    "Person437": {
        "month": 2,
        "day": 25
    },
    "Person438": {
        "month": 12,
        "day": 31
    },
    "Person439": {
        "month": 7,
        "day": 27
    },
    "Person440": {
        "month": 8,
        "day": 19
    },
    "Person441": {
        "month": 2,
        "day": 26
    },
    "Person442": {
        "month": 2,
        "day": 11
    },
    "Person443": {
        "month": 6,
        "day": 28
    },
    "Person444": {
        "month": 12,
        "day": 9
    },
    "Person445": {
        "month": 10,
        "day": 5
    },
    "Person446": {
        "month": 7,
        "day": 29
    },
    "Person447": {
        "month": 4,
        "day": 19
    },
    "Person448": {
        "month": 11,
        "day": 6
    },
    "Person449": {
        "month": 12,
        "day": 26
    },
    "Person450": {
        "month": 12,
        "day": 19
    },
    "Person451": {
        "month": 7,
        "day": 23
    },
    "Person452": {
        "month": 11,
        "day": 4
    },
    "Person453": {
        "month": 11,
        "day": 29
    },
    "Person454": {
        "month": 8,
        "day": 16
    },
    "Person455": {
        "month": 11,
        "day": 30
    },
    "Person456": {
        "month": 5,
        "day": 14
    },
    "Person457": {
        "month": 10,
        "day": 19
    },
    "Person458": {
        "month": 5,
        "day": 4
    },
    "Person459": {
        "month": 7,
        "day": 7
    },
    "Person460": {
        "month": 6,
        "day": 17
    },
    "Person461": {
        "month": 5,
        "day": 15
    },
    "Person462": {
        "month": 6,
        "day": 10
    },
    "Person463": {
        "month": 8,
        "day": 12
    },
    "Person516": {
        "month": 7,
        "day": 2
    },
    "Person517": {
        "month": 8,
        "day": 2
    },
    "Person518": {
        "month": 1,
        "day": 12
    },
    "Person519": {
        "month": 6,
        "day": 16
    },
    "Person520": {
        "month": 5,
        "day": 13
    },
    "Person521": {
        "month": 12,
        "day": 26
    },
    "Person522": {
        "month": 7,
        "day": 13
    },
    "Person523": {
        "month": 8,
        "day": 18
    },
    "Person524": {
        "month": 12,
        "day": 19
    },
    "Person525": {
        "month": 10,
        "day": 15
    },
    "Person526": {
        "month": 1,
        "day": 26
    },
    "Person527": {
        "month": 3,
        "day": 22
    },
    "Person528": {
        "month": 12,
        "day": 23
    },
    "Person529": {
        "month": 3,
        "day": 10
    },
    "Person530": {
        "month": 10,
        "day": 17
    },
    "Person531": {
        "month": 7,
        "day": 2
    },
    "Person532": {
        "month": 5,
        "day": 9
    },
    "Person533": {
        "month": 9,
        "day": 28
    },
    "Person534": {
        "month": 12,
        "day": 19
    },
    "Person535": {
        "month": 6,
        "day": 9
    },
    "Person536": {
        "month": 7,
        "day": 6
    },
    "Person537": {
        "month": 2,
        "day": 1
    },
    "Person538": {
        "month": 9,
        "day": 3
    },
    "Person539": {
        "month": 4,
        "day": 15
    },
    "Person540": {
        "month": 5,
        "day": 13
    },
    "Person541": {
        "month": 5,
        "day": 22
    },
    "Person542": {
        "month": 3,
        "day": 7
    },
    "Person543": {
        "month": 1,
        "day": 13
    },
    "Person544": {
        "month": 12,
        "day": 20
    },
    "Person545": {
        "month": 5,
        "day": 21
    },
    "Person546": {
        "month": 8,
        "day": 29
    },
    "Person547": {
        "month": 9,
        "day": 26
    },
    "Person548": {
        "month": 10,
        "day": 16
    },
    "Person549": {
        "month": 11,
        "day": 2
    },
    "Person550": {
        "month": 7,
        "day": 31
    },
    "Person551": {
        "month": 1,
        "day": 22
    },
    "Person552": {
        "month": 6,
        "day": 2
    },
    "Person553": {
        "month": 9,
        "day": 3
    },
    "Person554": {
        "month": 2,
        "day": 6
    },
    "Person555": {
        "month": 2,
        "day": 13
    },
    "Person556": {
        "month": 2,
        "day": 12
    },
    "Person557": {
        "month": 9,
        "day": 17
    },
    "Person558": {
        "month": 6,
        "day": 21
    },
    "Person559": {
        "month": 11,
        "day": 4
    },
    "Person560": {
        "month": 7,
        "day": 23
    },
    "Person561": {
        "month": 7,
        "day": 24
    },
    "Person562": {
        "month": 3,
        "day": 4
    },
    "Person563": {
        "month": 1,
        "day": 8
    },
    "Person564": {
        "month": 10,
        "day": 28
    },
    "Person565": {
        "month": 11,
        "day": 17
    },
    "Person566": {
        "month": 1,
        "day": 22
    },
    "Person567": {
        "month": 8,
        "day": 29
    },
    "Person568": {
        "month": 11,
        "day": 11
    },
    "Person569": {
        "month": 5,
        "day": 22
    },
    "Person570": {
        "month": 3,
        "day": 12
    },
    "Person571": {
        "month": 1,
        "day": 19
    },
    "Person572": {
        "month": 1,
        "day": 28
    },
    "Person573": {
        "month": 9,
        "day": 29
    },
    "Person574": {
        "month": 8,
        "day": 20
    },
    "Person575": {
        "month": 7,
        "day": 9
    },
    "Person576": {
        "month": 2,
        "day": 5
    },
    "Person577": {
        "month": 5,
        "day": 26
    },
    "Person578": {
        "month": 1,
        "day": 18
    },
    "Person579": {
        "month": 1,
        "day": 24
    },
    "Person580": {
        "month": 2,
        "day": 14
    },
    "Person581": {
        "month": 2,
        "day": 14
    },
    "Person582": {
        "month": 8,
        "day": 1
    },
    "Person583": {
        "month": 5,
        "day": 15
    },
    "Person584": {
        "month": 3,
        "day": 26
    },
    "Person585": {
        "month": 10,
        "day": 4
    },
    "Person586": {
        "month": 7,
        "day": 1
    },
    "Person587": {
        "month": 10,
        "day": 8
    },
    "Person588": {
        "month": 1,
        "day": 15
    },
    "Person589": {
        "month": 3,
        "day": 25
    },
    "Person590": {
        "month": 5,
        "day": 16
    },
    "Person591": {
        "month": 9,
        "day": 20
    },
    "Person592": {
        "month": 11,
        "day": 9
    },
    "Person593": {
        "month": 11,
        "day": 19
    },
    "Person594": {
        "month": 10,
        "day": 15
    },
    "Person595": {
        "month": 2,
        "day": 16
    },
    "Person596": {
        "month": 12,
        "day": 27
    },
    "Person597": {
        "month": 1,
        "day": 12
    },
    "Person598": {
        "month": 7,
        "day": 3
    },
    "Person599": {
        "month": 3,
        "day": 1
    },
    "Person600": {
        "month": 11,
        "day": 16
    },
    "Person601": {
        "month": 1,
        "day": 1
    },
    "Person602": {
        "month": 11,
        "day": 25
    },
    "Person603": {
        "month": 7,
        "day": 24
    },
    "Person604": {
        "month": 4,
        "day": 17
    },
    "Person605": {
        "month": 12,
        "day": 14
    },
    "Person606": {
        "month": 11,
        "day": 4
    },
    "Person607": {
        "month": 4,
        "day": 13
    },
    "Person608": {
        "month": 1,
        "day": 22
    },
    "Person609": {
        "month": 7,
        "day": 13
    },
    "Person610": {
        "month": 3,
        "day": 24
    },
    "Person611": {
        "month": 7,
        "day": 3
    },
    "Person612": {
        "month": 8,
        "day": 13
    },
    "Person613": {
        "month": 8,
        "day": 19
    },
    "Person614": {
        "month": 1,
        "day": 24
    },
    "Person615": {
        "month": 11,
        "day": 11
    },
    "Person616": {
        "month": 2,
        "day": 13
    },
    "Person617": {
        "month": 5,
        "day": 14
    },
    "Person618": {
        "month": 3,
        "day": 1
    },
    "Person619": {
        "month": 4,
        "day": 10
    },
    "Person620": {
        "month": 7,
        "day": 30
    },
    "Person621": {
        "month": 10,
        "day": 11
    },
    "Person622": {
        "month": 3,
        "day": 16
    },
    "Person623": {
        "month": 2,
        "day": 5
    },
    "Person624": {
        "month": 11,
        "day": 28
    },
    "Person625": {
        "month": 12,
        "day": 30
    },
    "Person626": {
        "month": 9,
        "day": 20
    },
    "Person627": {
        "month": 8,
        "day": 28
    },
    "Person628": {
        "month": 5,
        "day": 21
    },
    "Person629": {
        "month": 8,
        "day": 30
    },
    "Person630": {
        "month": 6,
        "day": 30
    },
    "Person631": {
        "month": 12,
        "day": 21
    },
    "Person632": {
        "month": 7,
        "day": 27
    },
    "Person633": {
        "month": 12,
        "day": 28
    },
    "Person634": {
        "month": 11,
        "day": 12
    },
    "Person635": {
        "month": 2,
        "day": 13
    },
    "Person636": {
        "month": 11,
        "day": 1
    },
    "Person637": {
        "month": 4,
        "day": 2
    },
    "Person638": {
        "month": 9,
        "day": 25
    },
    "Person639": {
        "month": 3,
        "day": 1
    },
    "Person640": {
        "month": 3,
        "day": 9
    },
    "Person641": {
        "month": 5,
        "day": 23
    },
    "Person642": {
        "month": 4,
        "day": 25
    },
    "Person643": {
        "month": 11,
        "day": 22
    },
    "Person644": {
        "month": 9,
        "day": 27
    },
    "Person645": {
        "month": 12,
        "day": 17
    },
    "Person646": {
        "month": 6,
        "day": 15
    },
    "Person647": {
        "month": 11,
        "day": 11
    },
    "Person648": {
        "month": 1,
        "day": 13
    },
    "Person649": {
        "month": 3,
        "day": 25
    },
    "Person650": {
        "month": 4,
        "day": 6
    },
    "Person651": {
        "month": 5,
        "day": 15
    },
    "Person652": {
        "month": 10,
        "day": 5
    },
    "Person653": {
        "month": 10,
        "day": 4
    },
    "Person654": {
        "month": 11,
        "day": 17
    },
    "Person655": {
        "month": 2,
        "day": 6
    },
    "Person656": {
        "month": 2,
        "day": 8
    },
    "Person657": {
        "month": 8,
        "day": 18
    },
    "Person658": {
        "month": 7,
        "day": 2
    },
    "Person659": {
        "month": 12,
        "day": 22
    },
    "Person660": {
        "month": 9,
        "day": 17
    },
    "Person661": {
        "month": 7,
        "day": 12
    },
    "Person662": {
        "month": 11,
        "day": 14
    },
    "Person663": {
        "month": 4,
        "day": 25
    },
    "Person664": {
        "month": 7,
        "day": 15
    },
    "Person665": {
        "month": 9,
        "day": 1
    },
    "Person666": {
        "month": 2,
        "day": 15
    },
    "Person667": {
        "month": 3,
        "day": 3
    },
    "Person668": {
        "month": 7,
        "day": 1
    },
    "Person669": {
        "month": 12,
        "day": 11
    },
    "Person670": {
        "month": 6,
        "day": 26
    },
    "Person671": {
        "month": 8,
        "day": 6
    },
    "Person672": {
        "month": 7,
        "day": 6
    },
    "Person673": {
        "month": 10,
        "day": 19
    },
    "Person674": {
        "month": 8,
        "day": 23
    },
    "Person675": {
        "month": 2,
        "day": 27
    },
    "Person676": {
        "month": 10,
        "day": 17
    },
    "Person677": {
        "month": 5,
        "day": 26
    },
    "Person678": {
        "month": 3,
        "day": 16
    },
    "Person679": {
        "month": 5,
        "day": 21
    },
    "Person680": {
        "month": 9,
        "day": 22
    },
    "Person681": {
        "month": 6,
        "day": 28
    },
    "Person682": {
        "month": 1,
        "day": 3
    },
    "Person683": {
        "month": 12,
        "day": 18
    },
    "Person684": {
        "month": 10,
        "day": 19
    },
    "Person685": {
        "month": 8,
        "day": 10
    },
    "Person686": {
        "month": 2,
        "day": 23
    },
    "Person687": {
        "month": 12,
        "day": 4
    },
    "Person688": {
        "month": 6,
        "day": 18
    },
    "Person689": {
        "month": 7,
        "day": 7
    },
    "Person690": {
        "month": 5,
        "day": 19
    },
    "Person691": {
        "month": 11,
        "day": 11
    },
    "Person692": {
        "month": 11,
        "day": 30
    },
    "Person693": {
        "month": 9,
        "day": 3
    },
    "Person694": {
        "month": 8,
        "day": 29
    },
    "Person695": {
        "month": 11,
        "day": 11
    },
    "Person696": {
        "month": 7,
        "day": 29
    },
    "Person697": {
        "month": 3,
        "day": 9
    },
    "Person698": {
        "month": 6,
        "day": 2
    },
    "Person699": {
        "month": 7,
        "day": 22
    },
    "Person700": {
        "month": 6,
        "day": 15
    },
    "Person701": {
        "month": 12,
        "day": 6
    },
    "Person702": {
        "month": 3,
        "day": 4
    },
    "Person703": {
        "month": 12,
        "day": 22
    },
    "Person704": {
        "month": 5,
        "day": 8
    },
    "Person705": {
        "month": 7,
        "day": 31
    },
    "Person706": {
        "month": 5,
        "day": 18
    },
    "Person707": {
        "month": 8,
        "day": 5
    },
    "Person708": {
        "month": 3,
        "day": 21
    },
    "Person709": {
        "month": 2,
        "day": 7
    },
    "Person710": {
        "month": 10,
        "day": 1
    },
    "Person711": {
        "month": 6,
        "day": 10
    },
    "Person712": {
        "month": 10,
        "day": 24
    },
    "Person713": {
        "month": 2,
        "day": 3
    },
    "Person714": {
        "month": 5,
        "day": 9
    },
    "Person715": {
        "month": 11,
        "day": 3
    },
    "Person716": {
        "month": 7,
        "day": 9
    },
    "Person717": {
        "month": 6,
        "day": 22
    },
    "Person718": {
        "month": 8,
        "day": 30
    },
    "Person719": {
        "month": 11,
        "day": 19
    },
    "Person720": {
        "month": 8,
        "day": 23
    },
    "Person721": {
        "month": 1,
        "day": 29
    },
    "Person722": {
        "month": 6,
        "day": 11
    },
    "Person723": {
        "month": 12,
        "day": 19
    },
    "Person724": {
        "month": 10,
        "day": 26
    },
    "Person725": {
        "month": 12,
        "day": 2
    },
    "Person726": {
        "month": 8,
        "day": 10
    },
    "Person727": {
        "month": 9,
        "day": 9
    },
    "Person728": {
        "month": 7,
        "day": 6
    },
    "Person729": {
        "month": 1,
        "day": 18
    },
    "Person730": {
        "month": 1,
        "day": 27
    },
    "Person731": {
        "month": 8,
        "day": 29
    },
    "Person732": {
        "month": 10,
        "day": 13
    },
    "Person733": {
        "month": 12,
        "day": 11
    },
    "Person734": {
        "month": 1,
        "day": 5
    },
    "Person735": {
        "month": 10,
        "day": 14
    },
    "Person736": {
        "month": 12,
        "day": 22
    },
    "Person737": {
        "month": 12,
        "day": 30
    },
    "Person738": {
        "month": 10,
        "day": 18
    },
    "Person739": {
        "month": 9,
        "day": 15
    },
    "Person740": {
        "month": 3,
        "day": 4
    },
    "Person741": {
        "month": 11,
        "day": 24
    },
    "Person742": {
        "month": 5,
        "day": 24
    },
    "Person743": {
        "month": 9,
        "day": 30
    },
    "Person744": {
        "month": 6,
        "day": 29
    },
    "Person745": {
        "month": 5,
        "day": 15
    },
    "Person746": {
        "month": 9,
        "day": 15
    },
    "Person747": {
        "month": 11,
        "day": 16
    },
    "Person748": {
        "month": 1,
        "day": 19
    },
    "Person749": {
        "month": 10,
        "day": 1
    },
    "Person750": {
        "month": 12,
        "day": 2
    },
    "Person751": {
        "month": 2,
        "day": 7
    },
    "Person752": {
        "month": 6,
        "day": 22
    },
    "Person753": {
        "month": 10,
        "day": 13
    },
    "Person754": {
        "month": 9,
        "day": 25
    },
    "Person755": {
        "month": 3,
        "day": 26
    },
    "Person756": {
        "month": 8,
        "day": 18
    },
    "Person757": {
        "month": 6,
        "day": 23
    },
    "Person758": {
        "month": 4,
        "day": 13
    },
    "Person759": {
        "month": 10,
        "day": 21
    },
    "Person760": {
        "month": 3,
        "day": 19
    },
    "Person761": {
        "month": 12,
        "day": 31
    },
    "Person762": {
        "month": 12,
        "day": 26
    },
    "Person763": {
        "month": 1,
        "day": 8
    },
    "Person764": {
        "month": 10,
        "day": 6
    },
    "Person765": {
        "month": 2,
        "day": 8
    },
    "Person766": {
        "month": 8,
        "day": 20
    },
    "Person767": {
        "month": 1,
        "day": 13
    },
    "Person768": {
        "month": 10,
        "day": 7
    },
    "Person769": {
        "month": 1,
        "day": 27
    },
    "Person770": {
        "month": 4,
        "day": 1
    },
    "Person771": {
        "month": 4,
        "day": 1
    },
    "Person772": {
        "month": 6,
        "day": 1
    },
    "Person773": {
        "month": 12,
        "day": 27
    },
    "Person774": {
        "month": 5,
        "day": 17
    },
    "Person775": {
        "month": 10,
        "day": 20
    },
    "Person776": {
        "month": 7,
        "day": 11
    },
    "Person777": {
        "month": 5,
        "day": 7
    },
    "Person778": {
        "month": 8,
        "day": 3
    },
    "Person779": {
        "month": 8,
        "day": 24
    },
    "Person780": {
        "month": 12,
        "day": 28
    },
    "Person781": {
        "month": 1,
        "day": 30
    },
    "Person782": {
        "month": 11,
        "day": 11
    },
    "Person783": {
        "month": 10,
        "day": 20
    },
    "Person784": {
        "month": 4,
        "day": 13
    },
    "Person785": {
        "month": 5,
        "day": 30
    },
    "Person786": {
        "month": 1,
        "day": 29
    },
    "Person787": {
        "month": 5,
        "day": 25
    },
    "Person788": {
        "month": 1,
        "day": 12
    },
    "Person789": {
        "month": 8,
        "day": 26
    },
    "Person790": {
        "month": 1,
        "day": 15
    },
    "Person791": {
        "month": 11,
        "day": 8
    },
    "Person792": {
        "month": 12,
        "day": 10
    },
    "Person793": {
        "month": 2,
        "day": 21
    },
    "Person794": {
        "month": 4,
        "day": 7
    },
    "Person795": {
        "month": 10,
        "day": 11
    },
    "Person796": {
        "month": 3,
        "day": 17
    },
    "Person797": {
        "month": 4,
        "day": 1
    },
    "Person798": {
        "month": 12,
        "day": 7
    },
    "Person799": {
        "month": 10,
        "day": 10
    },
    "Person800": {
        "month": 6,
        "day": 22
    },
    "Person801": {
        "month": 3,
        "day": 19
    },
    "Person802": {
        "month": 9,
        "day": 12
    },
    "Person803": {
        "month": 3,
        "day": 4
    },
    "Person804": {
        "month": 2,
        "day": 24
    },
    "Person805": {
        "month": 4,
        "day": 29
    },
    "Person806": {
        "month": 6,
        "day": 8
    },
    "Person807": {
        "month": 8,
        "day": 17
    },
    "Person808": {
        "month": 6,
        "day": 22
    },
    "Person809": {
        "month": 6,
        "day": 6
    },
    "Person810": {
        "month": 5,
        "day": 17
    },
    "Person811": {
        "month": 7,
        "day": 19
    },
    "Person812": {
        "month": 12,
        "day": 12
    },
    "Person813": {
        "month": 8,
        "day": 30
    },
    "Person814": {
        "month": 4,
        "day": 24
    },
    "Person815": {
        "month": 11,
        "day": 24
    },
    "Person816": {
        "month": 2,
        "day": 20
    },
    "Person817": {
        "month": 10,
        "day": 12
    },
    "Person818": {
        "month": 2,
        "day": 13
    },
    "Person819": {
        "month": 5,
        "day": 5
    },
    "Person820": {
        "month": 1,
        "day": 9
    },
    "Person821": {
        "month": 1,
        "day": 29
    },
    "Person822": {
        "month": 4,
        "day": 14
    },
    "Person823": {
        "month": 10,
        "day": 3
    },
    "Person824": {
        "month": 9,
        "day": 27
    },
    "Person825": {
        "month": 11,
        "day": 8
    },
    "Person826": {
        "month": 8,
        "day": 10
    },
    "Person827": {
        "month": 10,
        "day": 17
    },
    "Person828": {
        "month": 1,
        "day": 21
    },
    "Person829": {
        "month": 1,
        "day": 3
    },
    "Person830": {
        "month": 6,
        "day": 10
    },
    "Person831": {
        "month": 11,
        "day": 16
    },
    "Person832": {
        "month": 3,
        "day": 12
    },
    "Person833": {
        "month": 2,
        "day": 10
    },
    "Person834": {
        "month": 9,
        "day": 20
    },
    "Person835": {
        "month": 1,
        "day": 5
    },
    "Person836": {
        "month": 5,
        "day": 2
    },
    "Person837": {
        "month": 10,
        "day": 8
    },
    "Person838": {
        "month": 2,
        "day": 11
    },
    "Person839": {
        "month": 9,
        "day": 25
    },
    "Person840": {
        "month": 7,
        "day": 4
    },
    "Person841": {
        "month": 8,
        "day": 10
    },
    "Person842": {
        "month": 7,
        "day": 20
    },
    "Person843": {
        "month": 12,
        "day": 16
    },
    "Person844": {
        "month": 1,
        "day": 22
    },
    "Person845": {
        "month": 6,
        "day": 10
    },
    "Person846": {
        "month": 9,
        "day": 3
    },
    "Person847": {
        "month": 3,
        "day": 15
    },
    "Person848": {
        "month": 2,
        "day": 19
    },
    "Person849": {
        "month": 8,
        "day": 9
    },
    "Person850": {
        "month": 1,
        "day": 23
    },
    "Person851": {
        "month": 12,
        "day": 23
    },
    "Person852": {
        "month": 10,
        "day": 29
    },
    "Person853": {
        "month": 7,
        "day": 22
    },
    "Person854": {
        "month": 6,
        "day": 14
    },
    "Person855": {
        "month": 7,
        "day": 12
    },
    "Person856": {
        "month": 7,
        "day": 20
    },
    "Person857": {
        "month": 10,
        "day": 24
    },
    "Person858": {
        "month": 2,
        "day": 22
    },
    "Person859": {
        "month": 6,
        "day": 12
    },
    "Person860": {
        "month": 1,
        "day": 14
    },
    "Person861": {
        "month": 4,
        "day": 18
    },
    "Person862": {
        "month": 7,
        "day": 3
    },
    "Person863": {
        "month": 11,
        "day": 16
    },
    "Person864": {
        "month": 6,
        "day": 14
    },
    "Person865": {
        "month": 6,
        "day": 6
    },
    "Person866": {
        "month": 9,
        "day": 17
    },
    "Person867": {
        "month": 7,
        "day": 20
    },
    "Person868": {
        "month": 6,
        "day": 1
    },
    "Person869": {
        "month": 11,
        "day": 2
    },
    "Person870": {
        "month": 7,
        "day": 16
    },
    "Person871": {
        "month": 3,
        "day": 4
    },
    "Person872": {
        "month": 2,
        "day": 10
    },
    "Person873": {
        "month": 6,
        "day": 7
    },
    "Person874": {
        "month": 8,
        "day": 5
    },
    "Person875": {
        "month": 5,
        "day": 29
    },
    "Person876": {
        "month": 6,
        "day": 14
    },
    "Person877": {
        "month": 1,
        "day": 14
    },
    "Person878": {
        "month": 12,
        "day": 27
    },
    "Person879": {
        "month": 4,
        "day": 12
    },
    "Person880": {
        "month": 12,
        "day": 13
    },
    "Person881": {
        "month": 9,
        "day": 15
    },
    "Person882": {
        "month": 11,
        "day": 16
    },
    "Person883": {
        "month": 7,
        "day": 27
    },
    "Person884": {
        "month": 6,
        "day": 5
    },
    "Person885": {
        "month": 2,
        "day": 25
    },
    "Person886": {
        "month": 2,
        "day": 19
    },
    "Person887": {
        "month": 5,
        "day": 13
    },
    "Person888": {
        "month": 4,
        "day": 29
    },
    "Person889": {
        "month": 12,
        "day": 19
    },
    "Person890": {
        "month": 10,
        "day": 15
    },
    "Person891": {
        "month": 10,
        "day": 16
    },
    "Person892": {
        "month": 11,
        "day": 29
    },
    "Person893": {
        "month": 12,
        "day": 15
    },
    "Person894": {
        "month": 5,
        "day": 28
    },
    "Person895": {
        "month": 9,
        "day": 17
    },
    "Person896": {
        "month": 11,
        "day": 26
    },
    "Person897": {
        "month": 6,
        "day": 21
    },
    "Person898": {
        "month": 4,
        "day": 14
    },
    "Person899": {
        "month": 12,
        "day": 27
    },
    "Person900": {
        "month": 2,
        "day": 17
    },
    "Person901": {
        "month": 12,
        "day": 10
    },
    "Person902": {
        "month": 8,
        "day": 30
    },
    "Person903": {
        "month": 7,
        "day": 11
    },
    "Person904": {
        "month": 1,
        "day": 16
    },
    "Person905": {
        "month": 11,
        "day": 28
    },
    "Person906": {
        "month": 10,
        "day": 3
    },
    "Person907": {
        "month": 7,
        "day": 27
    },
    "Person908": {
        "month": 5,
        "day": 14
    },
    "Person909": {
        "month": 12,
        "day": 29
    },
    "Person910": {
        "month": 1,
        "day": 11
    },
    "Person911": {
        "month": 11,
        "day": 6
    },
    "Person912": {
        "month": 6,
        "day": 29
    },
    "Person913": {
        "month": 7,
        "day": 21
    },
    "Person914": {
        "month": 10,
        "day": 12
    },
    "Person915": {
        "month": 3,
        "day": 15
    },
    "Person916": {
        "month": 3,
        "day": 3
    },
    "Person917": {
        "month": 12,
        "day": 19
    },
    "Person918": {
        "month": 7,
        "day": 16
    },
    "Person919": {
        "month": 4,
        "day": 9
    },
    "Person920": {
        "month": 12,
        "day": 18
    },
    "Person921": {
        "month": 11,
        "day": 11
    },
    "Person922": {
        "month": 10,
        "day": 26
    },
    "Person923": {
        "month": 9,
        "day": 25
    },
    "Person924": {
        "month": 7,
        "day": 15
    },
    "Person925": {
        "month": 10,
        "day": 6
    },
    "Person926": {
        "month": 4,
        "day": 3
    },
    "Person927": {
        "month": 10,
        "day": 15
    },
    "Person928": {
        "month": 2,
        "day": 8
    },
    "Person929": {
        "month": 5,
        "day": 10
    },
    "Person930": {
        "month": 11,
        "day": 2
    },
    "Person931": {
        "month": 5,
        "day": 5
    },
    "Person932": {
        "month": 2,
        "day": 3
    },
    "Person933": {
        "month": 7,
        "day": 18
    },
    "Person934": {
        "month": 3,
        "day": 23
    },
    "Person935": {
        "month": 12,
        "day": 26
    },
    "Person936": {
        "month": 12,
        "day": 28
    },
    "Person937": {
        "month": 11,
        "day": 3
    },
    "Person938": {
        "month": 7,
        "day": 13
    },
    "Person939": {
        "month": 8,
        "day": 6
    },
    "Person940": {
        "month": 10,
        "day": 27
    },
    "Person941": {
        "month": 10,
        "day": 19
    },
    "Person942": {
        "month": 6,
        "day": 30
    },
    "Person943": {
        "month": 9,
        "day": 17
    },
    "Person944": {
        "month": 9,
        "day": 30
    },
    "Person945": {
        "month": 9,
        "day": 22
    },
    "Person946": {
        "month": 12,
        "day": 11
    },
    "Person947": {
        "month": 6,
        "day": 11
    },
    "Person948": {
        "month": 6,
        "day": 4
    },
    "Person949": {
        "month": 6,
        "day": 21
    },
    "Person950": {
        "month": 5,
        "day": 1
    },
    "Person951": {
        "month": 11,
        "day": 18
    },
    "Person952": {
        "month": 9,
        "day": 14
    },
    "Person953": {
        "month": 5,
        "day": 17
    },
    "Person954": {
        "month": 5,
        "day": 27
    },
    "Person955": {
        "month": 1,
        "day": 7
    },
    "Person956": {
        "month": 1,
        "day": 8
    },
    "Person957": {
        "month": 10,
        "day": 8
    },
    "Person958": {
        "month": 4,
        "day": 10
    },
    "Person959": {
        "month": 7,
        "day": 10
    },
    "Person960": {
        "month": 11,
        "day": 13
    },
    "Person961": {
        "month": 7,
        "day": 15
    },
    "Person962": {
        "month": 12,
        "day": 12
    },
    "Person963": {
        "month": 6,
        "day": 14
    },
    "Person964": {
        "month": 10,
        "day": 24
    },
    "Person965": {
        "month": 2,
        "day": 24
    },
    "Person966": {
        "month": 8,
        "day": 27
    },
    "Person967": {
        "month": 11,
        "day": 11
    },
    "Person968": {
        "month": 5,
        "day": 14
    },
    "Person969": {
        "month": 11,
        "day": 18
    },
    "Person970": {
        "month": 8,
        "day": 1
    },
    "Person971": {
        "month": 12,
        "day": 6
    },
    "Person972": {
        "month": 5,
        "day": 23
    },
    "Person973": {
        "month": 11,
        "day": 4
    },
    "Person974": {
        "month": 12,
        "day": 28
    },
    "Person975": {
        "month": 2,
        "day": 19
    },
    "Person976": {
        "month": 2,
        "day": 25
    },
    "Person977": {
        "month": 12,
        "day": 23
    },
    "Person978": {
        "month": 5,
        "day": 24
    },
    "Person979": {
        "month": 12,
        "day": 9
    },
    "Person980": {
        "month": 9,
        "day": 20
    },
    "Person981": {
        "month": 6,
        "day": 22
    },
    "Person982": {
        "month": 3,
        "day": 30
    },
    "Person983": {
        "month": 3,
        "day": 18
    },
    "Person984": {
        "month": 5,
        "day": 17
    },
    "Person985": {
        "month": 9,
        "day": 23
    },
    "Person986": {
        "month": 3,
        "day": 15
    },
    "Person987": {
        "month": 11,
        "day": 29
    },
    "Person988": {
        "month": 1,
        "day": 12
    },
    "Person989": {
        "month": 7,
        "day": 30
    },
    "Person990": {
        "month": 12,
        "day": 31
    },
    "Person991": {
        "month": 10,
        "day": 16
    },
    "Person992": {
        "month": 9,
        "day": 3
    },
    "Person997": {
        "month": 6,
        "day": 12
    },
    "Person999": {
        "month": 6,
        "day": 23
    },
    "hello": {
        "month": "1",
        "day": "1"
    }
}